ape_accounts/__init__.py
ape_accounts/__main__.py
ape_accounts/_cli.py
ape_accounts/accounts.py
ape_accounts/py.typed
ape_accounts/version.py
ape_accounts-0.1.0a1.dist-info/LICENSE
ape_accounts-0.1.0a1.dist-info/METADATA
ape_accounts-0.1.0a1.dist-info/WHEEL
ape_accounts-0.1.0a1.dist-info/top_level.txt
ape_accounts-0.1.0a1.dist-info/RECORD
