Metadata-Version: 2.1
Name: ape-accounts
Version: 0.1.0a1
Summary: Plugin for Ape Ethereum Framework for working with local accounts
Home-page: https://github.com/ApeWorX/ape-accounts
Author: ApeWorX Ltd.
Author-email: admin@apeworx.io
License: Apache-2.0
Keywords: ethereum
Platform: UNKNOWN
Classifier: Development Status :: 3 - Alpha
Classifier: Intended Audience :: Developers
Classifier: License :: OSI Approved :: MIT License
Classifier: Natural Language :: English
Classifier: Operating System :: MacOS
Classifier: Operating System :: POSIX
Classifier: Programming Language :: Python :: 3
Classifier: Programming Language :: Python :: 3.6
Classifier: Programming Language :: Python :: 3.7
Classifier: Programming Language :: Python :: 3.8
Classifier: Programming Language :: Python :: 3.9
Requires-Python: >=3.6,<4
Requires-Dist: eth-ape (>=0.1.0a2)
Provides-Extra: dev
Requires-Dist: pytest (<7.0,>=6.0) ; extra == 'dev'
Requires-Dist: pytest-xdist ; extra == 'dev'
Requires-Dist: pytest-cov ; extra == 'dev'
Requires-Dist: hypothesis (<7.0,>=6.2.0) ; extra == 'dev'
Requires-Dist: black (<21.0,>=20.8b1) ; extra == 'dev'
Requires-Dist: mypy (<1.0,>=0.800) ; extra == 'dev'
Requires-Dist: Sphinx (<4,>=3.4.3) ; extra == 'dev'
Requires-Dist: sphinx-rtd-theme (<1,>=0.1.9) ; extra == 'dev'
Requires-Dist: towncrier (<20,>=19.2.0) ; extra == 'dev'
Requires-Dist: setuptools ; extra == 'dev'
Requires-Dist: wheel ; extra == 'dev'
Requires-Dist: twine ; extra == 'dev'
Requires-Dist: commitizen ; extra == 'dev'
Requires-Dist: pytest-watch ; extra == 'dev'
Requires-Dist: IPython ; extra == 'dev'
Requires-Dist: ipdb ; extra == 'dev'
Provides-Extra: doc
Requires-Dist: Sphinx (<4,>=3.4.3) ; extra == 'doc'
Requires-Dist: sphinx-rtd-theme (<1,>=0.1.9) ; extra == 'doc'
Requires-Dist: towncrier (<20,>=19.2.0) ; extra == 'doc'
Provides-Extra: fuzz
Requires-Dist: pytest (<7.0,>=6.0) ; extra == 'fuzz'
Requires-Dist: pytest-xdist ; extra == 'fuzz'
Requires-Dist: pytest-cov ; extra == 'fuzz'
Requires-Dist: hypothesis (<7.0,>=6.2.0) ; extra == 'fuzz'
Provides-Extra: lint
Requires-Dist: black (<21.0,>=20.8b1) ; extra == 'lint'
Requires-Dist: mypy (<1.0,>=0.800) ; extra == 'lint'
Provides-Extra: release
Requires-Dist: setuptools ; extra == 'release'
Requires-Dist: wheel ; extra == 'release'
Requires-Dist: twine ; extra == 'release'
Provides-Extra: test
Requires-Dist: pytest (<7.0,>=6.0) ; extra == 'test'
Requires-Dist: pytest-xdist ; extra == 'test'
Requires-Dist: pytest-cov ; extra == 'test'
